huonu_yingdao/__init__.py
huonu_yingdao/example.py
huonu_yingdao-0.1.0.dist-info/METADATA
huonu_yingdao-0.1.0.dist-info/WHEEL
huonu_yingdao-0.1.0.dist-info/RECORD
