Metadata-Version: 2.4
Name: huonu-yingdao
Version: 0.1.0
Summary: A short description of your package
Project-URL: Homepage, https://github.com/yourusername/huonu-yingdao
Project-URL: Bug Tracker, https://github.com/yourusername/huonu-yingdao/issues
Author-email: Your Name <your.email@example.com>
License-Expression: MIT
Classifier: License :: OSI Approved :: MIT License
Classifier: Operating System :: OS Independent
Classifier: Programming Language :: Python :: 3
Requires-Python: >=3.6
